pyhugeconnector/__init__.py
pyhugeconnector/pyhugeconnector.py
pyhugeconnector-1.0.0.dist-info/DESCRIPTION.rst
pyhugeconnector-1.0.0.dist-info/METADATA
pyhugeconnector-1.0.0.dist-info/RECORD
pyhugeconnector-1.0.0.dist-info/WHEEL
pyhugeconnector-1.0.0.dist-info/metadata.json
pyhugeconnector-1.0.0.dist-info/top_level.txt
