Metadata-Version: 2.0
Name: pyhugeconnector
Version: 1.0.0
Summary: BigHugeThesaurus connector
Home-page: https://github.com/tttthomasssss/PyHugeThesaurusConnector
Author: tttthomasssss
Author-email: tttthomasssss@gmail.com
License: MIT
Keywords: nlp bighugethesaurus thesaurus
Platform: UNKNOWN
Classifier: Development Status :: 4 - Beta
Classifier: Intended Audience :: Developers
Classifier: Intended Audience :: Science/Research
Classifier: Topic :: Scientific/Engineering :: Artificial Intelligence
Classifier: Topic :: Software Development :: Libraries :: Python Modules
Classifier: License :: OSI Approved :: MIT License
Classifier: Programming Language :: Python :: 3
Classifier: Programming Language :: Python :: 3.2
Classifier: Programming Language :: Python :: 3.3
Classifier: Programming Language :: Python :: 3.4
Classifier: Programming Language :: Python :: 3.5
Classifier: Programming Language :: Python :: 3.6
Requires-Dist: requests (>=2.4.0)
